bidcap/__init__.py
bidcap/setup.py
bidcap/datasets/__init__.py
bidcap/datasets/cifar.py
bidcap/datasets/convex.py
bidcap/datasets/data.py
bidcap/datasets/mnist.py
bidcap/utils/__init__.py
bidcap/utils/loader.py
convtt/__init__.py
convtt/setup.py
convtt/analysis/__init__.py
convtt/analysis/analysis_test_accuracy.py
convtt/models/__init__.py
convtt/models/capsnet.py
convtt/models/densenet.py
convtt/models/dynamicnet.py
convtt/profile/__init__.py
convtt/profile/count_hooks.py
convtt/profile/utils.py
convtt/train/__init__.py
convtt/train/drivers.py
convtt/train/optimisers.py
convtt/train/trainer.py
convtt-0.0.2.data/scripts/analysis_test_accuracy.py
convtt-0.0.2.data/scripts/convtt_train_densenet.py
convtt-0.0.2.data/scripts/convtt_train_dynamicnet.py
cudam/__init__.py
cudam/setup.py
cudam/bin/__init__.py
cudam/bin/cudam_client.py
cudam/bin/cudam_run_code_dumb.py
cudam/bin/cudam_server.py
cudam/bin/cudam_snap_gpu.py
cudam/bin/cudam_task_manager.py
cudam/cuda/__init__.py
cudam/cuda/gpu/__init__.py
cudam/cuda/gpu/utils.py
cudam/cuda/task/__init__.py
cudam/cuda/task/shell_task.py
cudam/socket/__init__.py
cudam/socket/client/__init__.py
cudam/socket/client/request.py
cudam/socket/comm/__init__.py
cudam/socket/comm/logging.py
cudam/socket/comm/message.py
cudam/socket/comm/utils.py
cudam/socket/server/__init__.py
cudam/socket/server/request.py
convtt-0.0.2.dist-info/METADATA
convtt-0.0.2.dist-info/WHEEL
convtt-0.0.2.dist-info/top_level.txt
convtt-0.0.2.dist-info/RECORD
