Metadata-Version: 2.1
Name: convtt
Version: 0.0.2
Summary: Convolutional Neural Netoworks Training Tools
Home-page: https://github.com/wwwbbb8510/convtt.git
Author: Bin Wang
Author-email: wwwbbb8510@gmail.com
License: UNKNOWN
Platform: UNKNOWN
Classifier: Programming Language :: Python :: 3
Classifier: License :: OSI Approved :: MIT License
Classifier: Operating System :: OS Independent
